{
    "cardiovascular_system": {
        "description": "Heart and major blood vessels",
        "labels": [
            "heart",
            "aorta",
            "inferior_vena_cava",
            "superior_vena_cava",
            "left_iliac_artery",
            "right_iliac_artery",
            "left_iliac_vena",
            "right_iliac_vena",
            "left_brachiocephalic_vein",
            "right_brachiocephalic_vein",
            "left_common_carotid_artery",
            "right_common_carotid_artery",
            "brachiocephalic_trunk",
            "left_subclavian_artery",
            "right_subclavian_artery",
            "pulmonary_vein",
            "left_atrial_appendage",
            "portal_vein_and_splenic_vein",
            "hepatic_vessel"
        ]
    },
    "respiratory_system": {
        "description": "Lungs, airways, and respiratory structures",
        "labels": [
            "left_lung_upper_lobe",
            "left_lung_lower_lobe",
            "right_lung_upper_lobe",
            "right_lung_middle_lobe",
            "right_lung_lower_lobe",
            "trachea",
            "airway"
        ]
    },
    "gastrointestinal_system": {
        "description": "Digestive organs and structures",
        "labels": [
            "liver",
            "gallbladder",
            "pancreas",
            "esophagus",
            "stomach",
            "duodenum",
            "small_bowel",
            "colon"
        ]
    },
    "genitourinary_system": {
        "description": "Kidneys, bladder, and reproductive organs",
        "labels": [
            "right_kidney",
            "left_kidney",
            "right_kidney_cyst",
            "left_kidney_cyst",
            "bladder",
            "prostate"
        ]
    },
    "endocrine_system": {
        "description": "Hormone-producing glands",
        "labels": [
            "right_adrenal_gland",
            "left_adrenal_gland",
            "thyroid_gland"
        ]
    },
    "central_nervous_system": {
        "description": "Brain and spinal cord",
        "labels": [
            "brain",
            "spinal_cord",
            "skull"
        ]
    },
    "skeletal_system": {
        "description": "Bones and skeletal structures",
        "labels": [
            "left_humerus",
            "right_humerus",
            "left_scapula",
            "right_scapula",
            "left_clavicula",
            "right_clavicula",
            "left_femur",
            "right_femur",
            "left_hip",
            "right_hip",
            "sacrum",
            "sternum",
            "costal_cartilages",
            "bone_lesion"
        ]
    },
    "rib_cage_set": {
        "description": "All rib cage components",
        "labels": [
            "left_rib_1",
            "left_rib_2",
            "left_rib_3",
            "left_rib_4",
            "left_rib_5",
            "left_rib_6",
            "left_rib_7",
            "left_rib_8",
            "left_rib_9",
            "left_rib_10",
            "left_rib_11",
            "left_rib_12",
            "right_rib_1",
            "right_rib_2",
            "right_rib_3",
            "right_rib_4",
            "right_rib_5",
            "right_rib_6",
            "right_rib_7",
            "right_rib_8",
            "right_rib_9",
            "right_rib_10",
            "right_rib_11",
            "right_rib_12",
            "sternum",
            "costal_cartilages"
        ]
    },
    "vertebral_column": {
        "description": "All vertebrae and spinal structures",
        "labels": [
            "vertebrae_c1",
            "vertebrae_c2",
            "vertebrae_c3",
            "vertebrae_c4",
            "vertebrae_c5",
            "vertebrae_c6",
            "vertebrae_c7",
            "vertebrae_t1",
            "vertebrae_t2",
            "vertebrae_t3",
            "vertebrae_t4",
            "vertebrae_t5",
            "vertebrae_t6",
            "vertebrae_t7",
            "vertebrae_t8",
            "vertebrae_t9",
            "vertebrae_t10",
            "vertebrae_t11",
            "vertebrae_t12",
            "vertebrae_l1",
            "vertebrae_l2",
            "vertebrae_l3",
            "vertebrae_l4",
            "vertebrae_l5",
            "vertebrae_s1",
            "spinal_cord"
        ]
    },
    "muscular_system": {
        "description": "Muscles and soft tissues",
        "labels": [
            "left_gluteus_maximus",
            "right_gluteus_maximus",
            "left_gluteus_medius",
            "right_gluteus_medius",
            "left_gluteus_minimus",
            "right_gluteus_minimus",
            "left_autochthon",
            "right_autochthon",
            "left_iliopsoas",
            "right_iliopsoas"
        ]
    },
    "tumor_set": {
        "description": "All tumor and cancer-related structures",
        "labels": [
            "lung_tumor",
            "pancreatic_tumor",
            "hepatic_tumor",
            "colon_cancer_primaries",
            "bone_lesion"
        ]
    },
    "thoracic_organs": {
        "description": "Organs within the thoracic cavity",
        "labels": [
            "heart",
            "left_lung_upper_lobe",
            "left_lung_lower_lobe",
            "right_lung_upper_lobe",
            "right_lung_middle_lobe",
            "right_lung_lower_lobe",
            "trachea",
            "esophagus",
            "aorta",
            "superior_vena_cava",
            "inferior_vena_cava",
            "pulmonary_vein",
            "left_atrial_appendage",
            "brachiocephalic_trunk",
            "left_brachiocephalic_vein",
            "right_brachiocephalic_vein",
            "left_common_carotid_artery",
            "right_common_carotid_artery",
            "left_subclavian_artery",
            "right_subclavian_artery",
            "thyroid_gland"
        ]
    },
    "abdominal_organs": {
        "description": "Organs within the abdominal cavity",
        "labels": [
            "liver",
            "spleen",
            "pancreas",
            "right_kidney",
            "left_kidney",
            "right_kidney_cyst",
            "left_kidney_cyst",
            "right_adrenal_gland",
            "left_adrenal_gland",
            "gallbladder",
            "stomach",
            "duodenum",
            "small_bowel",
            "colon",
            "aorta",
            "inferior_vena_cava",
            "portal_vein_and_splenic_vein",
            "hepatic_vessel"
        ]
    },
    "pelvic_organs": {
        "description": "Organs within the pelvic cavity",
        "labels": [
            "bladder",
            "prostate",
            "left_iliac_artery",
            "right_iliac_artery",
            "left_iliac_vena",
            "right_iliac_vena",
            "sacrum",
            "left_hip",
            "right_hip"
        ]
    },
    "upper_limb": {
        "description": "Upper extremity structures",
        "labels": [
            "left_humerus",
            "right_humerus",
            "left_scapula",
            "right_scapula",
            "left_clavicula",
            "right_clavicula"
        ]
    },
    "lower_limb": {
        "description": "Lower extremity structures",
        "labels": [
            "left_femur",
            "right_femur",
            "left_hip",
            "right_hip",
            "left_gluteus_maximus",
            "right_gluteus_maximus",
            "left_gluteus_medius",
            "right_gluteus_medius",
            "left_gluteus_minimus",
            "right_gluteus_minimus",
            "left_autochthon",
            "right_autochthon",
            "left_iliopsoas",
            "right_iliopsoas"
        ]
    },
    "head_and_neck": {
        "description": "Cranial and cervical structures",
        "labels": [
            "brain",
            "skull",
            "thyroid_gland",
            "trachea",
            "esophagus",
            "left_common_carotid_artery",
            "right_common_carotid_artery",
            "left_subclavian_artery",
            "right_subclavian_artery",
            "vertebrae_c1",
            "vertebrae_c2",
            "vertebrae_c3",
            "vertebrae_c4",
            "vertebrae_c5",
            "vertebrae_c6",
            "vertebrae_c7"
        ]
    }
}
